lmk05318/__init__.py
lmk05318/__main__.py
lmk05318/console.py
lmk05318/lmk05318.py
ti_i2c_regs/__init__.py
ti_i2c_regs/lmk_i2c_regs.py
lmk05318-0.1.3.dist-info/LICENSE
lmk05318-0.1.3.dist-info/METADATA
lmk05318-0.1.3.dist-info/WHEEL
lmk05318-0.1.3.dist-info/top_level.txt
lmk05318-0.1.3.dist-info/RECORD
