Metadata-Version: 2.1
Name: LMK05318
Version: 0.1.3
Summary: A pure Python 3 library for LMK05318 device.
Home-page: https://github.com/oshevchenko/LMK05318.git
Author: Oleksandr Shevchenko
Author-email: shevchenko.adb@gmail.com
License: MIT
Keywords: LMK05318 pll embedded linux
Classifier: Development Status :: 4 - Beta
Classifier: License :: OSI Approved :: MIT License
Classifier: Operating System :: POSIX :: Linux
Classifier: Programming Language :: Python :: 3
Classifier: Programming Language :: Python :: 3 :: Only
Classifier: Topic :: Software Development :: Libraries :: Python Modules
Classifier: Topic :: Software Development :: Embedded Systems
Classifier: Topic :: System :: Hardware
Classifier: Topic :: System :: Hardware :: Hardware Drivers
Requires-Python: ~=3.7
License-File: LICENSE
